aasalert.py
aasalert-1.0.0.dist-info/LICENSE
aasalert-1.0.0.dist-info/METADATA
aasalert-1.0.0.dist-info/WHEEL
aasalert-1.0.0.dist-info/entry_points.txt
aasalert-1.0.0.dist-info/top_level.txt
aasalert-1.0.0.dist-info/RECORD
