Metadata-Version: 2.1
Name: aasalert
Version: 1.0.0
Summary: Search the AAS Job Register.
Home-page: https://github.com/AlecThomson/aasjobalert
Author: Alec Thomson
Author-email: alec.thomson@anu.edu.au
License: MIT License
Platform: UNKNOWN
Classifier: License :: OSI Approved :: MIT License
Classifier: Programming Language :: Python
Classifier: Programming Language :: Python :: 3
Classifier: Programming Language :: Python :: 3.6
Classifier: Programming Language :: Python :: Implementation :: CPython
Classifier: Intended Audience :: Science/Research
Classifier: Topic :: Scientific/Engineering :: Astronomy
Classifier: Development Status :: 3 - Alpha
Requires-Python: >=3.6.0
Requires-Dist: beautifulsoup4
Requires-Dist: requests
